{
  "type": "FeatureCollection",
  "features": [
    {
      "type": "Feature",
      "properties": {
        "offsetX": 30,
        "offsetY": -30,
        "rotation": 0
      },
      "geometry": {
        "coordinates": [
          [
            8.746287483066084,
            50.1373762548169
          ],
          [
            8.747029029602146,
            50.13771641622796
          ],
          [
            8.747497630408873,
            50.138016604843756
          ],
          [
            8.748624413618444,
            50.13839242377304
          ],
          [
            8.748748131304097,
            50.138441545421614
          ],
          [
            8.749122348723603,
            50.13882098822205
          ]
        ],
        "type": "LineString"
      }
    },
    {
      "type": "Feature",
      "properties": {
        "offsetX": 0,
        "offsetY": 30,
        "rotation": 0
      },
      "geometry": {
        "coordinates": [
          [
            8.746886132390408,
            50.13679238409426
          ],
          [
            8.747475648868152,
            50.13702680487103
          ],
          [
            8.748981007332452,
            50.137904174411545
          ],
          [
            8.748917740880273,
            50.13829150072023
          ],
          [
            8.750779139892831,
            50.13895751109007
          ]
        ],
        "type": "LineString"
      }
    }
  ]
}
